credentials_manager/__init__.py
credentials_manager/test_creds_manager.py
credentials_manager-0.2.dist-info/METADATA
credentials_manager-0.2.dist-info/WHEEL
credentials_manager-0.2.dist-info/top_level.txt
credentials_manager-0.2.dist-info/RECORD
